Metadata-Version: 2.1
Name: varstate
Version: 0.0.1
Summary: Python Package For Managing Data ReactJS State-Like.
Home-page: https://github.com/5elenay/varstate/
Author: 5elenay
Author-email: 
License: GNU General Public License v3 (GPLv3)
Project-URL: Bug Tracker, https://github.com/5elenay/varstate/issues
Keywords: state,python
Platform: UNKNOWN
Classifier: Development Status :: 5 - Production/Stable
Classifier: Intended Audience :: Developers
Classifier: Operating System :: OS Independent
Classifier: License :: OSI Approved :: GNU General Public License v3 (GPLv3)
Classifier: Programming Language :: Python :: 3
